{
    "/js/app.js": "/js/app.js",
    "/css/app.css": "/css/app.css",
    "/js/manifest.js": "/js/manifest.js",
    "/js/vendor.js": "/js/vendor.js",
    "/js/app.a411ead7142b18119af9.hot-update.js": "/js/app.a411ead7142b18119af9.hot-update.js",
    "/js/app.dbb69371532fd30663f1.hot-update.js": "/js/app.dbb69371532fd30663f1.hot-update.js",
    "/js/app.eb306d1b32e32d9aa9a7.hot-update.js": "/js/app.eb306d1b32e32d9aa9a7.hot-update.js",
    "/js/app.81a72816dfa298573c0d.hot-update.js": "/js/app.81a72816dfa298573c0d.hot-update.js",
    "/js/app.60f9a10750f0ff045ea8.hot-update.js": "/js/app.60f9a10750f0ff045ea8.hot-update.js",
    "/js/app.bfbbe67595dd86abbfe0.hot-update.js": "/js/app.bfbbe67595dd86abbfe0.hot-update.js",
    "/js/vendor.bfbbe67595dd86abbfe0.hot-update.js": "/js/vendor.bfbbe67595dd86abbfe0.hot-update.js",
    "/js/app.777194c0dae4922c626a.hot-update.js": "/js/app.777194c0dae4922c626a.hot-update.js",
    "/js/vendor.777194c0dae4922c626a.hot-update.js": "/js/vendor.777194c0dae4922c626a.hot-update.js",
    "/js/app.b2bad7d6079cad72e23d.hot-update.js": "/js/app.b2bad7d6079cad72e23d.hot-update.js",
    "/js/app.f06f268866755c46cfc4.hot-update.js": "/js/app.f06f268866755c46cfc4.hot-update.js",
    "/js/app.5ff4a756346f0dc27996.hot-update.js": "/js/app.5ff4a756346f0dc27996.hot-update.js",
    "/js/app.0b511dc6dd6311f0404a.hot-update.js": "/js/app.0b511dc6dd6311f0404a.hot-update.js",
    "/js/app.718ba35a48d3521f2c74.hot-update.js": "/js/app.718ba35a48d3521f2c74.hot-update.js",
    "/js/app.a8c6fab5701d0c4dbfd9.hot-update.js": "/js/app.a8c6fab5701d0c4dbfd9.hot-update.js",
    "/js/app.def85b4b3512c847e4f8.hot-update.js": "/js/app.def85b4b3512c847e4f8.hot-update.js",
    "/js/app.a2cc1f49cc1995afa79d.hot-update.js": "/js/app.a2cc1f49cc1995afa79d.hot-update.js",
    "/js/app.7eff0143eb4f6cca15e7.hot-update.js": "/js/app.7eff0143eb4f6cca15e7.hot-update.js",
    "/js/app.04468df0e59e2c9f0748.hot-update.js": "/js/app.04468df0e59e2c9f0748.hot-update.js",
    "/js/app.1bf47dca6176a1ea1542.hot-update.js": "/js/app.1bf47dca6176a1ea1542.hot-update.js",
    "/js/app.502020737b872dab0cb5.hot-update.js": "/js/app.502020737b872dab0cb5.hot-update.js",
    "/js/app.1af7bef90bf48980f047.hot-update.js": "/js/app.1af7bef90bf48980f047.hot-update.js",
    "/js/app.bc6ed3d4a44e1aaae184.hot-update.js": "/js/app.bc6ed3d4a44e1aaae184.hot-update.js",
    "/js/app.28e66005677dec390046.hot-update.js": "/js/app.28e66005677dec390046.hot-update.js",
    "/js/app.010f5cfebd26d092ce69.hot-update.js": "/js/app.010f5cfebd26d092ce69.hot-update.js",
    "/js/app.861d7a91a3950411261e.hot-update.js": "/js/app.861d7a91a3950411261e.hot-update.js",
    "/js/app.3a80d836f9310d014157.hot-update.js": "/js/app.3a80d836f9310d014157.hot-update.js",
    "/js/app.379d77660ac8e56f2962.hot-update.js": "/js/app.379d77660ac8e56f2962.hot-update.js",
    "/js/app.3c5bbafc17f97ff011fa.hot-update.js": "/js/app.3c5bbafc17f97ff011fa.hot-update.js",
    "/js/app.3e78b7043aedcf1767b2.hot-update.js": "/js/app.3e78b7043aedcf1767b2.hot-update.js",
    "/js/app.0c00a67182f0c8ba9fb7.hot-update.js": "/js/app.0c00a67182f0c8ba9fb7.hot-update.js",
    "/js/app.9b67b50518f82965d890.hot-update.js": "/js/app.9b67b50518f82965d890.hot-update.js",
    "/js/app.e3add990a639660463c3.hot-update.js": "/js/app.e3add990a639660463c3.hot-update.js",
    "/js/app.c141904618974a2a41c8.hot-update.js": "/js/app.c141904618974a2a41c8.hot-update.js",
    "/js/app.91944f2ac0d62702a63e.hot-update.js": "/js/app.91944f2ac0d62702a63e.hot-update.js",
    "/js/app.4cdc267ed1e8dafd1a7f.hot-update.js": "/js/app.4cdc267ed1e8dafd1a7f.hot-update.js",
    "/js/app.3593186e54341416a9ea.hot-update.js": "/js/app.3593186e54341416a9ea.hot-update.js",
    "/js/app.c86a2d2f66acf1584671.hot-update.js": "/js/app.c86a2d2f66acf1584671.hot-update.js",
    "/js/app.d8cc79c37d6498c3fb91.hot-update.js": "/js/app.d8cc79c37d6498c3fb91.hot-update.js",
    "/js/app.85bad289068b15a75619.hot-update.js": "/js/app.85bad289068b15a75619.hot-update.js",
    "/js/app.e8ec32a52d1167da47ae.hot-update.js": "/js/app.e8ec32a52d1167da47ae.hot-update.js",
    "/js/app.f253c7f94656b3b5b792.hot-update.js": "/js/app.f253c7f94656b3b5b792.hot-update.js",
    "/js/app.a29847f395af4946435a.hot-update.js": "/js/app.a29847f395af4946435a.hot-update.js",
    "/js/app.de4e65e93ed151d03fbf.hot-update.js": "/js/app.de4e65e93ed151d03fbf.hot-update.js",
    "/js/app.1a5affdd8e07816a812c.hot-update.js": "/js/app.1a5affdd8e07816a812c.hot-update.js",
    "/js/app.adc5abca3674d8ac1a39.hot-update.js": "/js/app.adc5abca3674d8ac1a39.hot-update.js",
    "/js/app.fc6e1f81fa5889099b56.hot-update.js": "/js/app.fc6e1f81fa5889099b56.hot-update.js",
    "/js/app.987f6b47f624a53a0d73.hot-update.js": "/js/app.987f6b47f624a53a0d73.hot-update.js",
    "/js/app.6e820a4668e339d5fac4.hot-update.js": "/js/app.6e820a4668e339d5fac4.hot-update.js",
    "/js/app.d1ea7ceb13534cf026ce.hot-update.js": "/js/app.d1ea7ceb13534cf026ce.hot-update.js"
}
